xmobar_wttr
