Metadata-Version: 2.1
Name: xmobar-wttr
Version: 0.2a0
Summary: An external xmobar plugin for customizable weather info!
Home-page: https://github.com/phdenzel/xmobar_wttr
Author: Philipp Denzel
Author-email: phdenzel@gmail.com
License: GNU General Public License v3.0
Platform: UNKNOWN
Classifier: Development Status :: 3 - Alpha
Classifier: License :: OSI Approved :: GNU General Public License v3 (GPLv3)
Classifier: Operating System :: POSIX
Classifier: Programming Language :: Python
Classifier: Programming Language :: Python :: 3
Classifier: Programming Language :: Python :: 3.6
Classifier: Programming Language :: Python :: 3.7
Classifier: Programming Language :: Python :: 3.8
Classifier: Programming Language :: Python :: 3.9
Requires-Python: >=3.6
License-File: LICENSE
